{
  "timestamp": "2025-06-01T12:05:04.267336",
  "scrape_date": "2025-06-01",
  "census_date": "2025-05-31",
  "facilities": {
    "in_facility": [
      {
        "Facility": "Curran-Fromhold Correctional Facility (CFCF)",
        "Adult males": 1310,
        "Adult females": 0,
        "Juvenile males": 0,
        "Juvenile females": 0
      },
      {
        "Facility": "Detention Center (DC)",
        "Adult males": 465,
        "Adult females": 0,
        "Juvenile males": 0,
        "Juvenile females": 0
      },
      {
        "Facility": "Detention Center Public Health Services Wing (DC PHSW)",
        "Adult males": 48,
        "Adult females": 6,
        "Juvenile males": 0,
        "Juvenile females": 0
      },
      {
        "Facility": "Philadelphia Industrial Correctional Center (PICC)",
        "Adult males": 639,
        "Adult females": 194,
        "Juvenile males": 0,
        "Juvenile females": 0
      },
      {
        "Facility": "Riverside Correctional Facility (RCF)",
        "Adult males": 624,
        "Adult females": 0,
        "Juvenile males": 0,
        "Juvenile females": 0
      },
      {
        "Facility": "Riverside Correctional Facility Alternative and Special Detention Central Unit (RCF ASDCU)",
        "Adult males": 0,
        "Adult females": 0,
        "Juvenile males": 0,
        "Juvenile females": 0
      },
      {
        "Facility": "Riverside Correctional Facility Alternative and Special Detention Modular Unit (RCF ASDMOD3)",
        "Adult males": 0,
        "Adult females": 0,
        "Juvenile males": 17,
        "Juvenile females": 0
      },
      {
        "Facility": "Weekenders",
        "Adult males": 2,
        "Adult females": 0,
        "Juvenile males": 0,
        "Juvenile females": 0
      },
      {
        "Facility": "In facility headcount total",
        "Adult males": 3088,
        "Adult females": 200,
        "Juvenile males": 17,
        "Juvenile females": 0
      }
    ],
    "temporarily_not_in_facility": [
      {
        "Facility": "Curran-Fromhold Correctional Facility (CFCF)",
        "Males": 1316,
        "Females": 0,
        "Total": 1316
      },
      {
        "Facility": "Detention Center (DC)",
        "Males": 466,
        "Females": 0,
        "Total": 466
      },
      {
        "Facility": "Detention Center Public Health Services Wing (DC PHSW)",
        "Males": 48,
        "Females": 6,
        "Total": 54
      },
      {
        "Facility": "Philadelphia Industrial Correctional Center (PICC)",
        "Males": 640,
        "Females": 197,
        "Total": 837
      },
      {
        "Facility": "Riverside Correctional Facility (RCF)",
        "Males": 624,
        "Females": 0,
        "Total": 624
      },
      {
        "Facility": "Riverside Correctional Facility Alternative and Special Detention Central Unit (RCF ASDCU)",
        "Males": 0,
        "Females": 0,
        "Total": 0
      },
      {
        "Facility": "Riverside Correctional Facility Alternative and Special Detention Modular Unit (RCF ASDMOD3)",
        "Males": 17,
        "Females": 0,
        "Total": 17
      },
      {
        "Facility": "Weekenders",
        "Males": 2,
        "Females": 0,
        "Total": 2
      },
      {
        "Facility": "In facility headcount and temporarily not in facility total",
        "Males": 3113,
        "Females": 203,
        "Total": 3316
      }
    ],
    "facility_totals": [],
    "other_jurisdictions": [
      {
        "Jurisdiction": "State Department of Corrections (DOC)",
        "Males": 0,
        "Females": 0,
        "Total": 0
      },
      {
        "Jurisdiction": "Juveniles",
        "Males": 0,
        "Females": 0,
        "Total": 0
      },
      {
        "Jurisdiction": "Delaware County",
        "Males": 0,
        "Females": 0,
        "Total": 0
      },
      {
        "Jurisdiction": "Lehigh County",
        "Males": 2,
        "Females": 0,
        "Total": 2
      },
      {
        "Jurisdiction": "All other jurisdictions",
        "Males": 162,
        "Females": 1,
        "Total": 163
      },
      {
        "Jurisdiction": "Total",
        "Males": 164,
        "Females": 1,
        "Total": 165
      }
    ],
    "total_population": [
      {
        "": "PDP in facility headcount and temporarily not in facility total",
        "Males": 3113,
        "Females": 203,
        "Total": 3316
      },
      {
        "": "Total PDP incarcerated people held in other jurisdictions",
        "Males": 164,
        "Females": 1,
        "Total": 165
      },
      {
        "": "Total",
        "Males": 3277,
        "Females": 204,
        "Total": 3481
      }
    ]
  }
}