{
  "timestamp": "2025-06-10T12:05:32.886453",
  "scrape_date": "2025-06-10",
  "census_date": "2025-06-09",
  "facilities": {
    "in_facility": [
      {
        "Facility": "Curran-Fromhold Correctional Facility (CFCF)",
        "Adult males": 1338,
        "Adult females": 0,
        "Juvenile males": 0,
        "Juvenile females": 0
      },
      {
        "Facility": "Detention Center (DC)",
        "Adult males": 481,
        "Adult females": 0,
        "Juvenile males": 0,
        "Juvenile females": 0
      },
      {
        "Facility": "Detention Center Public Health Services Wing (DC PHSW)",
        "Adult males": 44,
        "Adult females": 6,
        "Juvenile males": 0,
        "Juvenile females": 0
      },
      {
        "Facility": "Philadelphia Industrial Correctional Center (PICC)",
        "Adult males": 627,
        "Adult females": 209,
        "Juvenile males": 0,
        "Juvenile females": 0
      },
      {
        "Facility": "Riverside Correctional Facility (RCF)",
        "Adult males": 629,
        "Adult females": 0,
        "Juvenile males": 0,
        "Juvenile females": 0
      },
      {
        "Facility": "Riverside Correctional Facility Alternative and Special Detention Central Unit (RCF ASDCU)",
        "Adult males": 0,
        "Adult females": 0,
        "Juvenile males": 0,
        "Juvenile females": 0
      },
      {
        "Facility": "Riverside Correctional Facility Alternative and Special Detention Modular Unit (RCF ASDMOD3)",
        "Adult males": 0,
        "Adult females": 0,
        "Juvenile males": 16,
        "Juvenile females": 0
      },
      {
        "Facility": "Weekenders",
        "Adult males": 0,
        "Adult females": 0,
        "Juvenile males": 0,
        "Juvenile females": 0
      },
      {
        "Facility": "In facility headcount total",
        "Adult males": 3119,
        "Adult females": 215,
        "Juvenile males": 16,
        "Juvenile females": 0
      }
    ],
    "temporarily_not_in_facility": [
      {
        "Facility": "Curran-Fromhold Correctional Facility (CFCF)",
        "Males": 1344,
        "Females": 0,
        "Total": 1344
      },
      {
        "Facility": "Detention Center (DC)",
        "Males": 481,
        "Females": 0,
        "Total": 481
      },
      {
        "Facility": "Detention Center Public Health Services Wing (DC PHSW)",
        "Males": 45,
        "Females": 6,
        "Total": 51
      },
      {
        "Facility": "Philadelphia Industrial Correctional Center (PICC)",
        "Males": 627,
        "Females": 212,
        "Total": 839
      },
      {
        "Facility": "Riverside Correctional Facility (RCF)",
        "Males": 629,
        "Females": 0,
        "Total": 629
      },
      {
        "Facility": "Riverside Correctional Facility Alternative and Special Detention Central Unit (RCF ASDCU)",
        "Males": 0,
        "Females": 0,
        "Total": 0
      },
      {
        "Facility": "Riverside Correctional Facility Alternative and Special Detention Modular Unit (RCF ASDMOD3)",
        "Males": 16,
        "Females": 0,
        "Total": 16
      },
      {
        "Facility": "Weekenders",
        "Males": 0,
        "Females": 0,
        "Total": 0
      },
      {
        "Facility": "In facility headcount and temporarily not in facility total",
        "Males": 3142,
        "Females": 218,
        "Total": 3360
      }
    ],
    "facility_totals": [],
    "other_jurisdictions": [
      {
        "Jurisdiction": "State Department of Corrections (DOC)",
        "Males": 0,
        "Females": 0,
        "Total": 0
      },
      {
        "Jurisdiction": "Juveniles",
        "Males": 0,
        "Females": 0,
        "Total": 0
      },
      {
        "Jurisdiction": "Delaware County",
        "Males": 0,
        "Females": 0,
        "Total": 0
      },
      {
        "Jurisdiction": "Lehigh County",
        "Males": 2,
        "Females": 0,
        "Total": 2
      },
      {
        "Jurisdiction": "All other jurisdictions",
        "Males": 164,
        "Females": 1,
        "Total": 165
      },
      {
        "Jurisdiction": "Total",
        "Males": 166,
        "Females": 1,
        "Total": 167
      }
    ],
    "total_population": [
      {
        "": "PDP in facility headcount and temporarily not in facility total",
        "Males": 3142,
        "Females": 218,
        "Total": 3360
      },
      {
        "": "Total PDP incarcerated people held in other jurisdictions",
        "Males": 166,
        "Females": 1,
        "Total": 167
      },
      {
        "": "Total",
        "Males": 3308,
        "Females": 219,
        "Total": 3527
      }
    ]
  }
}