{
  "timestamp": "2026-03-17T12:15:08.788245",
  "scrape_date": "2026-03-17",
  "census_date": "2026-03-16",
  "facilities": {
    "in_facility": [
      {
        "Facility": "Curran-Fromhold Correctional Facility (CFCF)",
        "Adult males": 1429,
        "Adult females": 0,
        "Juvenile males": 0,
        "Juvenile females": 0
      },
      {
        "Facility": "Detention Center (DC)",
        "Adult males": 430,
        "Adult females": 0,
        "Juvenile males": 0,
        "Juvenile females": 0
      },
      {
        "Facility": "Detention Center Public Health Services Wing (DC PHSW)",
        "Adult males": 45,
        "Adult females": 4,
        "Juvenile males": 0,
        "Juvenile females": 0
      },
      {
        "Facility": "Philadelphia Industrial Correctional Center (PICC)",
        "Adult males": 544,
        "Adult females": 218,
        "Juvenile males": 0,
        "Juvenile females": 0
      },
      {
        "Facility": "Riverside Correctional Facility (RCF)",
        "Adult males": 526,
        "Adult females": 0,
        "Juvenile males": 0,
        "Juvenile females": 0
      },
      {
        "Facility": "Riverside Correctional Facility Alternative and Special Detention Central Unit (RCF ASDCU)",
        "Adult males": 0,
        "Adult females": 0,
        "Juvenile males": 0,
        "Juvenile females": 0
      },
      {
        "Facility": "Riverside Correctional Facility Alternative and Special Detention Modular Unit (RCF ASDMOD3)",
        "Adult males": 0,
        "Adult females": 0,
        "Juvenile males": 9,
        "Juvenile females": 0
      },
      {
        "Facility": "Weekenders",
        "Adult males": 0,
        "Adult females": 0,
        "Juvenile males": 0,
        "Juvenile females": 0
      },
      {
        "Facility": "In facility headcount total",
        "Adult males": 2974,
        "Adult females": 222,
        "Juvenile males": 9,
        "Juvenile females": 0
      }
    ],
    "temporarily_not_in_facility": [
      {
        "Facility": "Curran-Fromhold Correctional Facility (CFCF)",
        "Males": 1433,
        "Females": 0,
        "Total": 1433
      },
      {
        "Facility": "Detention Center (DC)",
        "Males": 431,
        "Females": 0,
        "Total": 431
      },
      {
        "Facility": "Detention Center Public Health Services Wing (DC PHSW)",
        "Males": 46,
        "Females": 4,
        "Total": 50
      },
      {
        "Facility": "Philadelphia Industrial Correctional Center (PICC)",
        "Males": 544,
        "Females": 219,
        "Total": 763
      },
      {
        "Facility": "Riverside Correctional Facility (RCF)",
        "Males": 527,
        "Females": 0,
        "Total": 527
      },
      {
        "Facility": "Riverside Correctional Facility Alternative and Special Detention Central Unit (RCF ASDCU)",
        "Males": 0,
        "Females": 0,
        "Total": 0
      },
      {
        "Facility": "Riverside Correctional Facility Alternative and Special Detention Modular Unit (RCF ASDMOD3)",
        "Males": 9,
        "Females": 0,
        "Total": 9
      },
      {
        "Facility": "Weekenders",
        "Males": 0,
        "Females": 0,
        "Total": 0
      },
      {
        "Facility": "In facility headcount and temporarily not in facility total",
        "Males": 2990,
        "Females": 223,
        "Total": 3213
      }
    ],
    "facility_totals": [],
    "other_jurisdictions": [
      {
        "Jurisdiction": "State Department of Corrections (DOC)",
        "Males": 0,
        "Females": 0,
        "Total": 0
      },
      {
        "Jurisdiction": "Juveniles",
        "Males": 0,
        "Females": 0,
        "Total": 0
      },
      {
        "Jurisdiction": "Delaware County",
        "Males": 0,
        "Females": 0,
        "Total": 0
      },
      {
        "Jurisdiction": "Lehigh County",
        "Males": 2,
        "Females": 0,
        "Total": 2
      },
      {
        "Jurisdiction": "All other jurisdictions",
        "Males": 156,
        "Females": 2,
        "Total": 158
      },
      {
        "Jurisdiction": "Total",
        "Males": 158,
        "Females": 2,
        "Total": 160
      }
    ],
    "total_population": [
      {
        "": "PDP in facility headcount and temporarily not in facility total",
        "Males": 2990,
        "Females": 223,
        "Total": 3213
      },
      {
        "": "Total PDP incarcerated people held in other jurisdictions",
        "Males": 158,
        "Females": 2,
        "Total": 160
      },
      {
        "": "Total",
        "Males": 3148,
        "Females": 225,
        "Total": 3373
      }
    ]
  }
}