{
  "timestamp": "2026-03-20T12:09:41.679693",
  "scrape_date": "2026-03-20",
  "census_date": "2026-03-19",
  "facilities": {
    "in_facility": [
      {
        "Facility": "Curran-Fromhold Correctional Facility (CFCF)",
        "Adult males": 1409,
        "Adult females": 0,
        "Juvenile males": 0,
        "Juvenile females": 0
      },
      {
        "Facility": "Detention Center (DC)",
        "Adult males": 425,
        "Adult females": 0,
        "Juvenile males": 0,
        "Juvenile females": 0
      },
      {
        "Facility": "Detention Center Public Health Services Wing (DC PHSW)",
        "Adult males": 41,
        "Adult females": 2,
        "Juvenile males": 0,
        "Juvenile females": 0
      },
      {
        "Facility": "Philadelphia Industrial Correctional Center (PICC)",
        "Adult males": 546,
        "Adult females": 215,
        "Juvenile males": 0,
        "Juvenile females": 0
      },
      {
        "Facility": "Riverside Correctional Facility (RCF)",
        "Adult males": 524,
        "Adult females": 0,
        "Juvenile males": 0,
        "Juvenile females": 0
      },
      {
        "Facility": "Riverside Correctional Facility Alternative and Special Detention Central Unit (RCF ASDCU)",
        "Adult males": 0,
        "Adult females": 0,
        "Juvenile males": 0,
        "Juvenile females": 0
      },
      {
        "Facility": "Riverside Correctional Facility Alternative and Special Detention Modular Unit (RCF ASDMOD3)",
        "Adult males": 0,
        "Adult females": 0,
        "Juvenile males": 8,
        "Juvenile females": 0
      },
      {
        "Facility": "Weekenders",
        "Adult males": 0,
        "Adult females": 0,
        "Juvenile males": 0,
        "Juvenile females": 0
      },
      {
        "Facility": "In facility headcount total",
        "Adult males": 2945,
        "Adult females": 217,
        "Juvenile males": 8,
        "Juvenile females": 0
      }
    ],
    "temporarily_not_in_facility": [
      {
        "Facility": "Curran-Fromhold Correctional Facility (CFCF)",
        "Males": 1411,
        "Females": 0,
        "Total": 1411
      },
      {
        "Facility": "Detention Center (DC)",
        "Males": 425,
        "Females": 0,
        "Total": 425
      },
      {
        "Facility": "Detention Center Public Health Services Wing (DC PHSW)",
        "Males": 43,
        "Females": 2,
        "Total": 45
      },
      {
        "Facility": "Philadelphia Industrial Correctional Center (PICC)",
        "Males": 546,
        "Females": 215,
        "Total": 761
      },
      {
        "Facility": "Riverside Correctional Facility (RCF)",
        "Males": 524,
        "Females": 0,
        "Total": 524
      },
      {
        "Facility": "Riverside Correctional Facility Alternative and Special Detention Central Unit (RCF ASDCU)",
        "Males": 0,
        "Females": 0,
        "Total": 0
      },
      {
        "Facility": "Riverside Correctional Facility Alternative and Special Detention Modular Unit (RCF ASDMOD3)",
        "Males": 8,
        "Females": 0,
        "Total": 8
      },
      {
        "Facility": "Weekenders",
        "Males": 0,
        "Females": 0,
        "Total": 0
      },
      {
        "Facility": "In facility headcount and temporarily not in facility total",
        "Males": 2957,
        "Females": 217,
        "Total": 3174
      }
    ],
    "facility_totals": [],
    "other_jurisdictions": [
      {
        "Jurisdiction": "State Department of Corrections (DOC)",
        "Males": 0,
        "Females": 0,
        "Total": 0
      },
      {
        "Jurisdiction": "Juveniles",
        "Males": 0,
        "Females": 0,
        "Total": 0
      },
      {
        "Jurisdiction": "Delaware County",
        "Males": 0,
        "Females": 0,
        "Total": 0
      },
      {
        "Jurisdiction": "Lehigh County",
        "Males": 2,
        "Females": 0,
        "Total": 2
      },
      {
        "Jurisdiction": "All other jurisdictions",
        "Males": 160,
        "Females": 2,
        "Total": 162
      },
      {
        "Jurisdiction": "Total",
        "Males": 162,
        "Females": 2,
        "Total": 164
      }
    ],
    "total_population": [
      {
        "": "PDP in facility headcount and temporarily not in facility total",
        "Males": 2957,
        "Females": 217,
        "Total": 3174
      },
      {
        "": "Total PDP incarcerated people held in other jurisdictions",
        "Males": 162,
        "Females": 2,
        "Total": 164
      },
      {
        "": "Total",
        "Males": 3119,
        "Females": 219,
        "Total": 3338
      }
    ]
  }
}